setup.py
surftrace/__init__.py
surftrace/baseDbParser.py
surftrace/baseParser.py
surftrace/dbParser.py
surftrace/execCmd.py
surftrace/ftrace.py
surftrace/fxpr.py
surftrace/gdbParser.py
surftrace/graphTree.py
surftrace/headTrans.py
surftrace/kobuild.py
surftrace/lbcClient.py
surftrace/prevPareser.py
surftrace/regSplit.py
surftrace/sobuild.py
surftrace/surfCommon.py
surftrace/surfElf.py
surftrace/surfException.py
surftrace/surfGraph.py
surftrace/surfThread.py
surftrace/surftrace.py
surftrace/uprobeParser.py
surftrace.egg-info/PKG-INFO
surftrace.egg-info/SOURCES.txt
surftrace.egg-info/dependency_links.txt
surftrace.egg-info/entry_points.txt
surftrace.egg-info/requires.txt
surftrace.egg-info/top_level.txt
surftrace.egg-info/zip-safe